jsonpath_rw_ext/__init__.py
jsonpath_rw_ext/_arithmetic.py
jsonpath_rw_ext/_filter.py
jsonpath_rw_ext/_iterable.py
jsonpath_rw_ext/_string.py
jsonpath_rw_ext/parser.py
jsonpath_rw_ext/tests/__init__.py
jsonpath_rw_ext/tests/test_jsonpath_rw_ext.py
jsonpath_rw_ext-1.2.0.dist-info/DESCRIPTION.rst
jsonpath_rw_ext-1.2.0.dist-info/METADATA
jsonpath_rw_ext-1.2.0.dist-info/RECORD
jsonpath_rw_ext-1.2.0.dist-info/WHEEL
jsonpath_rw_ext-1.2.0.dist-info/metadata.json
jsonpath_rw_ext-1.2.0.dist-info/pbr.json
jsonpath_rw_ext-1.2.0.dist-info/top_level.txt
