Metadata-Version: 1.1
Name: jsonpath-rw-ext
Version: 1.2.0
Summary: Extensions for JSONPath RW
Home-page: https://github.com/sileht/python-jsonpath-rw-ext
Author: Mehdi Abaakouk
Author-email: sileht@sileht.net
License: UNKNOWN
Platform: UNKNOWN
Classifier: Development Status :: 5 - Production/Stable
Classifier: Intended Audience :: Developers
Classifier: License :: OSI Approved :: Apache Software License
Classifier: Programming Language :: Python
Classifier: Programming Language :: Python :: 2
Classifier: Programming Language :: Python :: 2.7
Classifier: Programming Language :: Python :: 3
Classifier: Programming Language :: Python :: 3.3
Classifier: Programming Language :: Python :: 3.4
